sodapy/__init__.py
sodapy/constants.py
sodapy/socrata.py
sodapy/utils.py
sodapy/version.py
sodapy-2.2.0.dist-info/LICENSE
sodapy-2.2.0.dist-info/METADATA
sodapy-2.2.0.dist-info/WHEEL
sodapy-2.2.0.dist-info/top_level.txt
sodapy-2.2.0.dist-info/RECORD
