Metadata-Version: 2.1
Name: sodapy
Version: 2.2.0
Summary: Python library for the Socrata Open Data API
Home-page: https://github.com/xmunoz/sodapy
Author: Cristina Muñoz
Author-email: hi@xmunoz.com
Maintainer: Cristina Muñoz
Maintainer-email: hi@xmunoz.com
License: MIT
Download-URL: https://github.com/xmunoz/sodapy/archive/master.tar.gz
Keywords: soda socrata opendata api
Platform: UNKNOWN
Classifier: Programming Language :: Python :: 3
Classifier: Topic :: Software Development :: Libraries :: Python Modules
Classifier: License :: OSI Approved :: MIT License
Classifier: Operating System :: OS Independent
Classifier: Development Status :: 5 - Production/Stable
License-File: LICENSE
